nonebot_plugin_warframe_clock/__init__.py
nonebot_plugin_warframe_clock/data/font1.ttf
nonebot_plugin_warframe_clock/data/夜灵背景.png
nonebot_plugin_warframe_clock/data/时间背景.png
nonebot_plugin_warframe_clock/data_source.py
nonebot_plugin_warframe_clock-1.3.dist-info/LICENSE
nonebot_plugin_warframe_clock-1.3.dist-info/WHEEL
nonebot_plugin_warframe_clock-1.3.dist-info/METADATA
nonebot_plugin_warframe_clock-1.3.dist-info/RECORD
