Metadata-Version: 2.1
Name: nonebot-plugin-warframe-clock
Version: 1.3
Summary: nonebot2插件，查询Warframe开放地图时间。
License: MIT
Author: Aa
Author-email: 2272613209@qq.com
Requires-Python: >=3.9,<4.0
Classifier: License :: OSI Approved :: MIT License
Classifier: Programming Language :: Python :: 3
Classifier: Programming Language :: Python :: 3.10
Classifier: Programming Language :: Python :: 3.9
Requires-Dist: Pillow (>=9.1.1,<10.0.0)
Requires-Dist: arrow (>=1.2.2,<2.0.0)
Requires-Dist: httpx (>=0.23.0,<0.24.0)
Requires-Dist: nonebot-adapter-onebot (>=2.0.0-beta.1,<3.0.0)
Requires-Dist: nonebot2 (==2.0.0b3)
